{
  "_lookup": ["name"],
  "_translate": ["title"],
  "name": "segments",
  "title": "Segments",
  "extends": "Contact",
  "style": "Tab with table",
  "collapse_display": "0",
  "is_active": "1",
  "is_multiple": "1",
  "table_name": "civicrm_segmentation",
  "collapse_adv_display": "0",
  "is_reserved": "0",
  "_fields": [
    {
      "_lookup": ["column_name"],
      "_translate": ["label"],
      "name": "Date",
      "label": "Date",
      "data_type": "Date",
      "html_type": "Select Date",
      "is_required": "0",
      "is_searchable": "0",
      "is_search_range": "0",
      "is_active": "1",
      "is_view": "1",
      "text_length": "255",
      "date_format": "yy-mm-dd",
      "time_format": "2",
      "column_name": "datetime",
      "in_selector": "1"
    },
    {
      "_lookup": ["column_name"],
      "_translate": ["label"],
      "name": "Campaign",
      "label": "Campaign",
      "data_type": "Int",
      "html_type": "Text",
      "is_required": "0",
      "is_searchable": "1",
      "is_search_range": "0",
      "is_active": "1",
      "is_view": "1",
      "text_length": "255",
      "note_columns": "60",
      "note_rows": "4",
      "column_name": "campaign_id",
      "in_selector": "1"
    },
    {
      "_lookup": ["column_name"],
      "_translate": ["label"],
      "name": "Segment",
      "label": "Segment",
      "data_type": "String",
      "html_type": "Select",
      "option_group_id": "segments",
      "is_required": "0",
      "is_searchable": "1",
      "is_search_range": "0",
      "weight": "3",
      "is_active": "1",
      "is_view": "1",
      "text_length": "32",
      "column_name": "segment_id",
      "in_selector": "1"
    },
    {
      "_lookup": ["column_name"],
      "_translate": ["label"],
      "name": "Testgroup",
      "label": "Testgroup",
      "data_type": "String",
      "html_type": "Text",
      "is_required": "0",
      "is_searchable": "1",
      "is_search_range": "0",
      "weight": "3",
      "is_active": "1",
      "is_view": "1",
      "text_length": "32",
      "column_name": "test_group",
      "in_selector": "1"
    },
    {
      "_lookup": ["column_name"],
      "_translate": ["label"],
      "name": "Membership",
      "label": "Membership",
      "data_type": "Int",
      "html_type": "Text",
      "is_required": "0",
      "is_searchable": "1",
      "is_search_range": "0",
      "is_active": "1",
      "is_view": "1",
      "text_length": "255",
      "note_columns": "60",
      "note_rows": "4",
      "column_name": "membership_id",
      "in_selector": "1"
    }
  ]
}