<?xml version="1.0"?>
<menu>
  <item>
    <path>civicrm/segmentation/start</path>
    <page_callback>CRM_Segmentation_Page_Start</page_callback>
    <title>Start Campaign</title>
    <access_arguments>access CiviCRM</access_arguments>
  </item>
  <item>
    <path>civicrm/segmentation/export</path>
    <page_callback>CRM_Segmentation_Form_Export</page_callback>
    <title>Export Campaign</title>
    <access_arguments>access CiviCRM</access_arguments>
  </item>
  <item>
    <path>civicrm/segmentation/contacts</path>
    <page_callback>CRM_Segmentation_Page_ContactList</page_callback>
    <title>Contact List</title>
    <access_arguments>access CiviCRM</access_arguments>
  </item>
  <item>
    <path>civicrm/segmentation/download</path>
    <page_callback>CRM_Segmentation_Page_Download</page_callback>
    <title>Download</title>
    <access_arguments>access CiviCRM</access_arguments>
  </item>
  <item>
    <path>civicrm/segmentation/createactivity</path>
    <page_callback>CRM_Segmentation_Form_CreateActivity</page_callback>
    <title>CreateActivity</title>
    <access_arguments>access CiviCRM</access_arguments>
  </item>
  <item>
    <path>civicrm/segmentation/split</path>
    <page_callback>CRM_Segmentation_Form_Split</page_callback>
    <title>Split</title>
    <access_arguments>access CiviCRM</access_arguments>
  </item>
</menu>
